hat/manager/__init__.py
hat/manager/__main__.py
hat/manager/common.py
hat/manager/json_schema_repo.json
hat/manager/main.py
hat/manager/server.py
hat/manager/devices/__init__.py
hat/manager/devices/event.py
hat/manager/devices/iec104.py
hat/manager/devices/modbus.py
hat/manager/devices/monitor.py
hat/manager/devices/orchestrator.py
hat/manager/ui/favicon.ico
hat/manager/ui/index.html
hat/manager/ui/main.js
hat/manager/ui/main.js.map
hat/manager/ui/fonts/FontAwesome/FontAwesome.woff2
hat/manager/ui/fonts/Inter/Inter.woff2
hat/manager/ui/fonts/Inter/OFL.txt
hat/manager/ui/fonts/RobotoMono/LICENSE.txt
hat/manager/ui/fonts/RobotoMono/RobotoMono-Italic.woff2
hat/manager/ui/fonts/RobotoMono/RobotoMono.woff2
hat/manager/ui/icons/hat.png
hat/manager/ui/icons/iec.png
hat/manager/ui/icons/modbus.png
hat_manager-0.5.7.dist-info/LICENSE
hat_manager-0.5.7.dist-info/METADATA
hat_manager-0.5.7.dist-info/WHEEL
hat_manager-0.5.7.dist-info/entry_points.txt
hat_manager-0.5.7.dist-info/top_level.txt
hat_manager-0.5.7.dist-info/zip-safe
hat_manager-0.5.7.dist-info/RECORD
