Metadata-Version: 2.1
Name: hat-manager
Version: 0.5.7
Summary: Hat manager
Home-page: https://github.com/hat-open/hat-manager
License: Apache-2.0
Classifier: Programming Language :: Python :: 3
Classifier: License :: OSI Approved :: Apache Software License
Requires-Python: >=3.8
License-File: LICENSE
Requires-Dist: appdirs (~=1.4.4)
Requires-Dist: hat-aio (~=0.7.0)
Requires-Dist: hat-drivers (~=0.5.17)
Requires-Dist: hat-event (~=0.7.6)
Requires-Dist: hat-json (~=0.5.8)
Requires-Dist: hat-juggler (~=0.5.9)
Requires-Dist: hat-monitor (~=0.6.4)
Requires-Dist: hat-util (~=0.5.8)
